act/__init__.py
act/config.py
act/corrections/__init__.py
act/corrections/ceil.py
act/corrections/doppler_lidar.py
act/corrections/mpl.py
act/corrections/raman_lidar.py
act/corrections/ship.py
act/discovery/__init__.py
act/discovery/airnow.py
act/discovery/ameriflux.py
act/discovery/arm.py
act/discovery/asos.py
act/discovery/cropscape.py
act/discovery/improve.py
act/discovery/nasa.py
act/discovery/neon.py
act/discovery/noaapsl.py
act/discovery/surfrad.py
act/io/__init__.py
act/io/ameriflux.py
act/io/arm.py
act/io/hysplit.py
act/io/icartt.py
act/io/mpl.py
act/io/neon.py
act/io/noaagml.py
act/io/noaapsl.py
act/io/pysp2.py
act/io/sodar.py
act/io/text.py
act/io/conf/noaapsl_SurfaceMet.yaml
act/plotting/__init__.py
act/plotting/common.py
act/plotting/contourdisplay.py
act/plotting/distributiondisplay.py
act/plotting/geodisplay.py
act/plotting/plot.py
act/plotting/skewtdisplay.py
act/plotting/timeseriesdisplay.py
act/plotting/windrosedisplay.py
act/plotting/xsectiondisplay.py
act/qc/__init__.py
act/qc/add_supplemental_qc.py
act/qc/arm.py
act/qc/bsrn_tests.py
act/qc/clean.py
act/qc/comparison_tests.py
act/qc/qc_summary.py
act/qc/qcfilter.py
act/qc/qctests.py
act/qc/radiometer_tests.py
act/qc/sp2.py
act/retrievals/__init__.py
act/retrievals/aeri.py
act/retrievals/cbh.py
act/retrievals/doppler_lidar.py
act/retrievals/irt.py
act/retrievals/pbl_lidar.py
act/retrievals/radiation.py
act/retrievals/sonde.py
act/retrievals/sp2.py
act/tests/__init__.py
act/tests/sample_files.py
act/utils/__init__.py
act/utils/data_utils.py
act/utils/datetime_utils.py
act/utils/geo_utils.py
act/utils/inst_utils.py
act/utils/io_utils.py
act/utils/qc_utils.py
act/utils/radiance_utils.py
act/utils/ship_utils.py
act/utils/conf/de421.bsp
act_atmos-2.3.0.dist-info/licenses/LICENSE.txt
act_atmos-2.3.0.dist-info/METADATA
act_atmos-2.3.0.dist-info/WHEEL
act_atmos-2.3.0.dist-info/entry_points.txt
act_atmos-2.3.0.dist-info/top_level.txt
act_atmos-2.3.0.dist-info/RECORD
