Metadata-Version: 2.4
Name: act-atmos
Version: 2.3.0
Summary: Package for working with atmospheric time series datasets
Author-email: Adam Theisen <atheisen@anl.gov>
License-Expression: BSD-3-Clause
Project-URL: Homepage, https://github.com/ARM-DOE/ACT
Platform: Linux
Platform: Mac OS-X
Platform: Unix
Platform: Windows
Classifier: Development Status :: 5 - Production/Stable
Classifier: Natural Language :: English
Classifier: Programming Language :: Python :: 3
License-File: LICENSE.txt
Requires-Dist: pyproj
Requires-Dist: numpy
Requires-Dist: pandas
Requires-Dist: matplotlib
Requires-Dist: scipy
Requires-Dist: xarray
Requires-Dist: dask
Requires-Dist: distributed
Requires-Dist: pint
Requires-Dist: requests
Requires-Dist: six
Requires-Dist: skyfield
Requires-Dist: cftime
Requires-Dist: netcdf4
Requires-Dist: lazy_loader
Requires-Dist: fsspec
Requires-Dist: metpy
Requires-Dist: lxml
Requires-Dist: cmweather
Requires-Dist: arm-test-data
Requires-Dist: openpyxl
Requires-Dist: aiohttp>=3.9.0b1
Provides-Extra: dev
Dynamic: license-file
